nonebot_plugin_ai_topia/__init__.py
nonebot_plugin_ai_topia/config.py
nonebot_plugin_ai_topia/Login.py
nonebot_plugin_ai_topia-0.1.3.dist-info/LICENSE
nonebot_plugin_ai_topia-0.1.3.dist-info/METADATA
nonebot_plugin_ai_topia-0.1.3.dist-info/WHEEL
nonebot_plugin_ai_topia-0.1.3.dist-info/RECORD
