Metadata-Version: 2.3
Name: nonebot_plugin_ai_topia
Version: 0.1.3
Summary: nonebot2AI乌托邦pro对话插件
License: MIT License
Keywords: nonebot2,nonebot
Author: kanzakiD
Author-email: 1690800500@qq.com
Requires-Python: >=3.13,<4.0
Classifier: License :: Other/Proprietary License
Classifier: Programming Language :: Python :: 3
Classifier: Programming Language :: Python :: 3.13
Requires-Dist: httpx (>=0.28.1)
Requires-Dist: nonebot-plugin-localstore (>=0.7.3)
Requires-Dist: nonebot2 (>=2.4.1)
Requires-Dist: pydantic (>=2.10.3)
Project-URL: Homepage, https://github.com/kanzakiD/nonebot_plugin_ai_topia
